<?xml version="1.0"?>
<wikiPage>
  <title>Choc</title>
  <categories><category>Pathfinder-RPG.Non-officiel</category><category>Pathfinder-RPG.Sort</category><category>Pathfinder-RPG.Sort magicien 0</category></categories>
  <lastModified>2013-12-07 00:43:19Z</lastModified>
  <version>1</version>
  <inLinks><link>Pathfinder-RPG.Glossaire des sorts</link><link>Pathfinder-RPG.Liste des sorts</link><link>Pathfinder-RPG.Liste des sorts densorceleursmagiciens</link><link>Pathfinder-RPG.Liste des sorts par registre</link></inLinks>
  <outLinks><link>Pathfinder-RPG.Transmutation</link><link>Pathfinder-RPG.Registre</link><link>Pathfinder-RPG.Ensorceleur</link><link>Pathfinder-RPG.Magicien</link><link>Pathfinder-RPG.Action simple</link><link>Pathfinder-RPG.composantes</link><link>Pathfinder-RPG.niveau</link><link>Pathfinder-RPG.attaque de contact à distance</link></outLinks>
  <body><![CDATA[&lt;b&gt;&#201;cole&lt;/b&gt; &lt;a class=&quot;pagelink&quot; href=&quot;Pr&#233;sentation-Des-Sorts.html#TRANSMUTATION&quot; title=&quot;Transmutation&quot;&gt;Transmutation&lt;/a&gt; [&lt;a class=&quot;pagelink&quot; href=&quot;Cr&#233;er-Un-Sort.html#REGISTRE&quot; title=&quot;Registre&quot;&gt;&#233;lectricit&#233;&lt;/a&gt;]; &lt;b&gt;Niveau&lt;/b&gt; &lt;a class=&quot;pagelink&quot; href=&quot;Ensorceleur.html&quot; title=&quot;L&amp;#39;ensorceleur&quot;&gt;ensorceleur&lt;/a&gt;/&lt;a class=&quot;pagelink&quot; href=&quot;Magicien.html&quot; title=&quot;Le magicien&quot;&gt;magicien&lt;/a&gt; 0&lt;br /&gt;
&lt;b&gt;Temps d’incantation&lt;/b&gt; 1 &lt;a class=&quot;pagelink&quot; href=&quot;Types-Dactions.html#SIMPLE&quot; title=&quot;Action simple&quot;&gt;action simple&lt;/a&gt;&lt;br /&gt;
&lt;b&gt;Composantes&lt;/b&gt; &lt;a class=&quot;pagelink&quot; href=&quot;Pr&#233;sentation-Des-Sorts.html#COMPOSANTES&quot; title=&quot;composantes&quot;&gt;V, G&lt;/a&gt;&lt;br /&gt;
&lt;b&gt;Port&#233;e&lt;/b&gt; courte (7,50 m + 1,50 m/2 &lt;a class=&quot;pagelink&quot; href=&quot;Vocabulaire-Courant.html#NIVEAU&quot; title=&quot;niveau&quot;&gt;niveaux&lt;/a&gt;) / (5 &lt;abbr title=&quot;cases&quot;&gt;c&lt;/abbr&gt; + 1 &lt;abbr title=&quot;cases&quot;&gt;c&lt;/abbr&gt;/2 &lt;a class=&quot;pagelink&quot; href=&quot;Vocabulaire-Courant.html#NIVEAU&quot; title=&quot;niveau&quot;&gt;niveaux&lt;/a&gt;)&lt;br /&gt;
&lt;b&gt;Effet&lt;/b&gt; &#233;tincelle d&#39;&#233;lectricit&#233;&lt;br /&gt;
&lt;b&gt;Dur&#233;e&lt;/b&gt; instantan&#233;e&lt;br /&gt;
&lt;b&gt;Jet de sauvegarde&lt;/b&gt; aucun ; &lt;b&gt;R&#233;sistance &#224; la magie&lt;/b&gt; oui&lt;br /&gt;&lt;br /&gt;Une &#233;tincelle d’&#233;lectricit&#233; vient frapper la cible sur un jet r&#233;ussi d’&lt;a class=&quot;pagelink&quot; href=&quot;Valeurs-De-Combat.html#ATTAQUESDECONTACT&quot; title=&quot;attaque de contact &#224; distance&quot;&gt;attaque de contact &#224; distance&lt;/a&gt;. Elle provoque 1d3 points de d&#233;g&#226;ts d’&#233;lectricit&#233;.&lt;br /&gt;&lt;br /&gt;&lt;div class=&quot;box&quot;&gt;&lt;b&gt;Note :&lt;/b&gt; La parution de ces nouveaux tours de magie &#233;tait initialement pr&#233;vue par Paizo dans l’Art de la Magie. Elle a &#233;t&#233; supprim&#233;e faute de place, en laissant des traces dans la premi&#232;re &#233;dition de l’ouvrage en anglais. Paizo a d&#233;cid&#233; de faire plaisir &#224; ses fans en les publiant par la suite sur son blog. BBE et Pathfinder-FR sont particuli&#232;rement heureux de pouvoir en proposer autant aux fans francophones.&lt;br /&gt;
Le sort ci-dessous est diff&#233;rent des tours de magie habituels. Il est rare. Les lanceurs de sorts qui ont acc&#232;s &#224; tous les sorts de niveau 0 d&#232;s leur premier niveau ne b&#233;n&#233;ficient pas de ce sort. Un lanceur de sorts doit d&#233;couvrir son secret d’une autre fa&#231;on (grimoire de mage, biblioth&#232;ques, parchemins oubli&#233;s...).&lt;br /&gt;
Ce tour de magie ne peut &#234;tre utilis&#233; dans le cadre du jeu organis&#233; de la Pathfinder Society.&lt;/div&gt;
]]></body>
  <raw><![CDATA['''École''' [[Transmutation]] <nowiki>[</nowiki>[[registre|électricité]]<nowiki>]</nowiki>; '''Niveau''' [[ensorceleur]]/[[magicien]] 0<br>
'''Temps d’incantation''' 1 [[action simple]]<br>
'''Composantes''' [[Composantes|V, G]]<br>
'''Portée''' courte (7,50 m + 1,50 m/2 [[niveau|niveaux]]) / (5 {s:c} + 1 {s:c}/2 [[niveau|niveaux]])<br>
'''Effet''' étincelle d'électricité<br>
'''Durée''' instantanée<br>
'''Jet de sauvegarde''' aucun ; '''Résistance à la magie''' oui

Une étincelle d’électricité vient frapper la cible sur un jet réussi d’[[attaque de contact à distance]]. Elle provoque 1d3 points de dégâts d’électricité.

((('''Note :''' La parution de ces nouveaux tours de magie était initialement prévue par Paizo dans l’Art de la Magie. Elle a été supprimée faute de place, en laissant des traces dans la première édition de l’ouvrage en anglais. Paizo a décidé de faire plaisir à ses fans en les publiant par la suite sur son blog. BBE et Pathfinder-FR sont particulièrement heureux de pouvoir en proposer autant aux fans francophones.<br>
Le sort ci-dessous est différent des tours de magie habituels. Il est rare. Les lanceurs de sorts qui ont accès à tous les sorts de niveau 0 dès leur premier niveau ne bénéficient pas de ce sort. Un lanceur de sorts doit découvrir son secret d’une autre façon (grimoire de mage, bibliothèques, parchemins oubliés...).<br>
Ce tour de magie ne peut être utilisé dans le cadre du jeu organisé de la Pathfinder Society.)))]]></raw>
  <fullName>Pathfinder-RPG.Choc</fullName>
</wikiPage>