<?xml version="1.0"?>
<wikiPage>
  <title>Pouvoir magique rapide</title>
  <categories><category>Pathfinder-RPG.Don</category><category>Pathfinder-RPG.Don monstre</category></categories>
  <lastModified>2010-11-11 12:23:07Z</lastModified>
  <version>2</version>
  <inLinks><link>Pathfinder-RPG.Alraune</link><link>Pathfinder-RPG.Asurendra</link><link>Pathfinder-RPG.Balor</link><link>Pathfinder-RPG.Barégare</link><link>Pathfinder-RPG.Chernobue</link><link>Pathfinder-RPG.Coloxe</link><link>Pathfinder-RPG.Croquemitaine</link><link>Pathfinder-RPG.Démodande hirsute</link><link>Pathfinder-RPG.Derghodaémon</link><link>Pathfinder-RPG.Diable osseux</link><link>Pathfinder-RPG.Diantrefosse</link><link>Pathfinder-RPG.Dons pour monstres</link><link>Pathfinder-RPG.Efrit</link><link>Pathfinder-RPG.grand au-delà</link><link>Pathfinder-RPG.Iathavos</link><link>Pathfinder-RPG.Kékétar</link><link>Pathfinder-RPG.Kolyarut</link><link>Pathfinder-RPG.Marcheur ténébreux</link><link>Pathfinder-RPG.Méladaémon</link><link>Pathfinder-RPG.Néothélide</link><link>Pathfinder-RPG.Norne</link><link>Pathfinder-RPG.Oléthrodaémon</link><link>Pathfinder-RPG.page de travail des dons</link><link>Pathfinder-RPG.Phoenix</link><link>Pathfinder-RPG.Rampant ténébreux</link><link>Pathfinder-RPG.Reine thriae</link><link>Pathfinder-RPG.Roussalka</link><link>Pathfinder-RPG.Sard</link><link>Pathfinder-RPG.Shaitan</link><link>Pathfinder-RPG.Tableau récapitulatif des dons</link><link>Pathfinder-RPG.Thulgant</link><link>Pathfinder-RPG.Vague ténébreuse</link><link>Pathfinder-RPG.Vrolikai</link></inLinks>
  <outLinks><link>Pathfinder-RPG.attaque dopportunité</link><link>Pathfinder-RPG.Action rapide</link></outLinks>
  <body><![CDATA[&lt;i&gt;La cr&#233;ature peut utiliser un de ses pouvoirs magiques quasiment sans effort.&lt;/i&gt;&lt;br /&gt;&lt;br /&gt;&lt;b&gt;Cat&#233;gorie.&lt;/b&gt; Monstre&lt;br /&gt;&lt;br /&gt;&lt;b&gt;Condition.&lt;/b&gt; Poss&#233;der un pouvoir magique lanc&#233; &#224; un NLS sup&#233;rieur ou &#233;gal &#224; 10.&lt;br /&gt;&lt;br /&gt;&lt;b&gt;Avantage.&lt;/b&gt; Ce don s’applique &#224; un des pouvoirs magiques de la cr&#233;ature, qui doit v&#233;rifier les conditions d&#233;crites ci-dessous. Trois fois par jour (ou moins souvent si la cr&#233;ature est normalement limit&#233;e &#224; une ou deux utilisations quotidiennes du pouvoir), le pouvoir choisi peut &#234;tre utilis&#233; de mani&#232;re rapide.
Une action rapide suffit pour activer le pouvoir, et celle-ci ne provoque pas d’&lt;a class=&quot;pagelink&quot; href=&quot;Valeurs-De-Combat.html#ATTAQUEDOPPORTUNITE&quot; title=&quot;attaque d&amp;#39;opportunit&#233;&quot;&gt;attaque d’opportunit&#233;&lt;/a&gt;. La cr&#233;ature peut entreprendre d’autres actions au cours du m&#234;me round (utiliser un autre pouvoir magique par exemple, mais pas une autre &lt;a class=&quot;pagelink&quot; href=&quot;Types-Dactions.html#RAPIDE&quot; title=&quot;Action rapide&quot;&gt;action rapide&lt;/a&gt;). Elle ne peut utiliser qu’un seul pouvoir magique rapide par round.
Le pouvoir magique choisi doit imiter un sort dont le niveau est inf&#233;rieur ou &#233;gal &#224; la moiti&#233; du NLS de la cr&#233;ature (arrondi vers le bas) moins 4. Le tableau ci-dessous pr&#233;sente les restrictions impos&#233;es par cette condition.&lt;br /&gt;&lt;br /&gt;&lt;b&gt;Sp&#233;cial.&lt;/b&gt; La cr&#233;ature peut gagner ce don plusieurs fois, mais ses effets ne se cumulent pas : il s’applique chaque fois &#224; un pouvoir magique diff&#233;rent.&lt;br /&gt;&lt;br /&gt;&lt;center&gt;
&lt;table CLASS=&quot;tablo&quot; WIDTH=&quot;50%&quot;&gt;&lt;caption&gt;Pouvoirs magiques &#224; effets rapides&lt;/caption&gt;&lt;tr CLASS=&quot;titre&quot;&gt;&lt;td&gt;Niveau du sort&lt;/td&gt;&lt;td&gt;NLS minimal pour utilisation rapide&lt;/td&gt;&lt;/tr&gt;&lt;tr CLASS=&quot;premier&quot;&gt;&lt;td&gt;0&lt;/td&gt;&lt;td&gt;8&lt;/td&gt;&lt;/tr&gt;&lt;tr CLASS=&quot;alt&quot;&gt;&lt;td&gt;1 &lt;/td&gt;&lt;td&gt;10&lt;/td&gt;&lt;/tr&gt;&lt;tr&gt;&lt;td&gt;2&lt;/td&gt;&lt;td&gt;12&lt;/td&gt;&lt;/tr&gt;&lt;tr CLASS=&quot;alt&quot;&gt;&lt;td&gt;3&lt;/td&gt;&lt;td&gt;14&lt;/td&gt;&lt;/tr&gt;&lt;tr&gt;&lt;td&gt;4&lt;/td&gt;&lt;td&gt;16&lt;/td&gt;&lt;/tr&gt;&lt;tr CLASS=&quot;alt&quot;&gt;&lt;td&gt;5&lt;/td&gt;&lt;td&gt;18&lt;/td&gt;&lt;/tr&gt;&lt;tr&gt;&lt;td&gt;6&lt;/td&gt;&lt;td&gt;20&lt;/td&gt;&lt;/tr&gt;&lt;tr CLASS=&quot;alt&quot;&gt;&lt;td&gt;7&lt;/td&gt;&lt;td&gt;—&lt;/td&gt;&lt;/tr&gt;&lt;tr&gt;&lt;td&gt;8&lt;/td&gt;&lt;td&gt;—&lt;/td&gt;&lt;/tr&gt;&lt;tr CLASS=&quot;alt&quot;&gt;&lt;td&gt;9&lt;/td&gt;&lt;td&gt;—&lt;/td&gt;&lt;/tr&gt;&lt;/table&gt;
&lt;/center&gt;
]]></body>
  <raw><![CDATA[''La créature peut utiliser un de ses pouvoirs magiques quasiment sans effort.''

'''Catégorie.''' Monstre

'''Condition.''' Posséder un pouvoir magique lancé à un NLS supérieur ou égal à 10.

'''Avantage.''' Ce don s’applique à un des pouvoirs magiques de la créature, qui doit vérifier les conditions décrites ci-dessous. Trois fois par jour (ou moins souvent si la créature est normalement limitée à une ou deux utilisations quotidiennes du pouvoir), le pouvoir choisi peut être utilisé de manière rapide.
Une action rapide suffit pour activer le pouvoir, et celle-ci ne provoque pas d’[[attaque dopportunité|attaque d’opportunité]]. La créature peut entreprendre d’autres actions au cours du même round (utiliser un autre pouvoir magique par exemple, mais pas une autre [[action rapide]]). Elle ne peut utiliser qu’un seul pouvoir magique rapide par round.
Le pouvoir magique choisi doit imiter un sort dont le niveau est inférieur ou égal à la moitié du NLS de la créature (arrondi vers le bas) moins 4. Le tableau ci-dessous présente les restrictions imposées par cette condition.

'''Spécial.''' La créature peut gagner ce don plusieurs fois, mais ses effets ne se cumulent pas : il s’applique chaque fois à un pouvoir magique différent.

<center>
{| CLASS="tablo" WIDTH="50%"
|+ Pouvoirs magiques à effets rapides
|- CLASS="titre"
| Niveau du sort
| NLS minimal pour utilisation rapide
|- CLASS="premier"
| 0
| 8
|- CLASS="alt"
| 1 
| 10
|-
| 2
| 12
|- CLASS="alt"
| 3
| 14
|-
| 4
| 16
|- CLASS="alt"
| 5
| 18
|-
| 6
| 20
|- CLASS="alt"
| 7
| —
|-
| 8
| —
|- CLASS="alt"
| 9
| —
|}
</center>]]></raw>
  <fullName>Pathfinder-RPG.Pouvoir magique rapide</fullName>
</wikiPage>