<?xml version="1.0"?>
<wikiPage>
  <title>Évasion</title>
  <categories><category>Pathfinder-RPG.Compétence</category></categories>
  <lastModified>2010-07-05 13:41:38Z</lastModified>
  <version>8</version>
  <inLinks><link>Pathfinder-RPG.Adhukaït</link><link>Pathfinder-RPG.Aghasura</link><link>Pathfinder-RPG.Anguille électrique</link><link>Pathfinder-RPG.Anneaux de transport</link><link>Pathfinder-RPG.Aranéa</link><link>Pathfinder-RPG.Archer (guerrier)</link><link>Pathfinder-RPG.Archon messager</link><link>Pathfinder-RPG.Armure de contorsionniste</link><link>Pathfinder-RPG.Armures magiques</link><link>Pathfinder-RPG.Arpenteur dhorizon</link><link>Pathfinder-RPG.Assassin</link><link>Pathfinder-RPG.Astradaémon</link><link>Pathfinder-RPG.Asurendra</link><link>Pathfinder-RPG.Atomie</link><link>Pathfinder-RPG.Babau</link><link>Pathfinder-RPG.Barde</link><link>Pathfinder-RPG.Belette</link><link>Pathfinder-RPG.Berbalang</link><link>Pathfinder-RPG.Bête du Chaos</link><link>Pathfinder-RPG.Bhuta</link><link>Pathfinder-RPG.Blaireau</link><link>Pathfinder-RPG.Blaireau sanguinaire</link><link>Pathfinder-RPG.Brijidine</link><link>Pathfinder-RPG.Caractéristiques</link><link>Pathfinder-RPG.Casse-cou (barde)</link><link>Pathfinder-RPG.Chaînes dimensionnelles</link><link>Pathfinder-RPG.Chapeau rouge</link><link>Pathfinder-RPG.Chernobue</link><link>Pathfinder-RPG.Chroniqueur</link><link>Pathfinder-RPG.Collet</link><link>Pathfinder-RPG.Compagnons animaux</link><link>Pathfinder-RPG.Compétences</link><link>Pathfinder-RPG.Corde animée</link><link>Pathfinder-RPG.Corde denchevêtrement</link><link>Pathfinder-RPG.Courses poursuites</link><link>Pathfinder-RPG.Croquemitaine</link><link>Pathfinder-RPG.Crucidaémon</link><link>Pathfinder-RPG.Danse-sort (magus)</link><link>Pathfinder-RPG.Décapus</link><link>Pathfinder-RPG.Demi-elfe</link><link>Pathfinder-RPG.Déplacement et position</link><link>Pathfinder-RPG.Descriptions individuelles des armes</link><link>Pathfinder-RPG.Désenchanteur</link><link>Pathfinder-RPG.Dévoreur dâmes</link><link>Pathfinder-RPG.Diable vestale</link><link>Pathfinder-RPG.Disciple draconien</link><link>Pathfinder-RPG.Discret</link><link>Pathfinder-RPG.Domaine des Serpents</link><link>Pathfinder-RPG.dons relatifs aux compétences</link><link>Pathfinder-RPG.Draconal</link><link>Pathfinder-RPG.Dragon de magma</link><link>Pathfinder-RPG.Dragon impérial des forêts</link><link>Pathfinder-RPG.Dretch</link><link>Pathfinder-RPG.Dryade</link><link>Pathfinder-RPG.Duelliste</link><link>Pathfinder-RPG.eidolon</link><link>Pathfinder-RPG.Élémentaire de la boue</link><link>Pathfinder-RPG.Élémentaire de la glace</link><link>Pathfinder-RPG.Élémentaire de lAir</link><link>Pathfinder-RPG.Élémentaire de lEau</link><link>Pathfinder-RPG.Élémentaire de léclair</link><link>Pathfinder-RPG.Élémentaire du Feu</link><link>Pathfinder-RPG.Enchevêtrement</link><link>Pathfinder-RPG.Entrave (arme magique)</link><link>Pathfinder-RPG.Érinye</link><link>Pathfinder-RPG.Esprit follet</link><link>Pathfinder-RPG.États préjudiciables</link><link>Pathfinder-RPG.évolutions</link><link>Pathfinder-RPG.Fabricant de pistolets expérimentaux (pistolier)</link><link>Pathfinder-RPG.FAQ Combat</link><link>Pathfinder-RPG.Farfadet</link><link>Pathfinder-RPG.Feu-follet</link><link>Pathfinder-RPG.Fiélon sargasse</link><link>Pathfinder-RPG.Fixation (capacité)</link><link>Pathfinder-RPG.Flot obsidien</link><link>Pathfinder-RPG.Fuath</link><link>Pathfinder-RPG.Fuite renversante</link><link>Pathfinder-RPG.Ghaéle</link><link>Pathfinder-RPG.Gilet dévasion</link><link>Pathfinder-RPG.Glossaire des compétences</link><link>Pathfinder-RPG.Graisse</link><link>Pathfinder-RPG.Grig</link><link>Pathfinder-RPG.Gug</link><link>Pathfinder-RPG.Habitantdelalumiere</link><link>Pathfinder-RPG.Hezrou</link><link>Pathfinder-RPG.Homme-serpent</link><link>Pathfinder-RPG.Iathavos</link><link>Pathfinder-RPG.Incube</link><link>Pathfinder-RPG.Invocateur sauvage (conjurateur)</link><link>Pathfinder-RPG.Jabberwocky</link><link>Pathfinder-RPG.Jiang-shi</link><link>Pathfinder-RPG.Jinkin</link><link>Pathfinder-RPG.Kappa</link><link>Pathfinder-RPG.Kodama</link><link>Pathfinder-RPG.Kyton</link><link>Pathfinder-RPG.Kyton augure</link><link>Pathfinder-RPG.Liberté de mouvement</link><link>Pathfinder-RPG.Liens dacier mystiques</link><link>Pathfinder-RPG.lignage Aberrant</link><link>Pathfinder-RPG.lignage serpentin</link><link>Pathfinder-RPG.Loutre</link><link>Pathfinder-RPG.Lutin</link><link>Pathfinder-RPG.MainPage</link><link>Pathfinder-RPG.Maître chymiste</link><link>Pathfinder-RPG.Maître des bêtes (rôdeur)</link><link>Pathfinder-RPG.Maître des ombres</link><link>Pathfinder-RPG.Maître espion</link><link>Pathfinder-RPG.Malotru (guerrier)</link><link>Pathfinder-RPG.Manœuvres offensives</link><link>Pathfinder-RPG.Matériel daventurier</link><link>Pathfinder-RPG.Matériel de classes et de compétences</link><link>Pathfinder-RPG.Mihstu</link><link>Pathfinder-RPG.Moine</link><link>Pathfinder-RPG.Murène géante</link><link>Pathfinder-RPG.Mystère des vagues</link><link>Pathfinder-RPG.Mystère du vent</link><link>Pathfinder-RPG.Mystificateur profane</link><link>Pathfinder-RPG.naga corrupteur</link><link>Pathfinder-RPG.Naga ténébreux</link><link>Pathfinder-RPG.Nappe de goudron</link><link>Pathfinder-RPG.Néréide</link><link>Pathfinder-RPG.Ninja</link><link>Pathfinder-RPG.Nixe</link><link>Pathfinder-RPG.Nixie</link><link>Pathfinder-RPG.Nuckelavee</link><link>Pathfinder-RPG.Nymphe</link><link>Pathfinder-RPG.Omox</link><link>Pathfinder-RPG.Onguent dinsaisissabilité</link><link>Pathfinder-RPG.Ordre libérateur</link><link>Pathfinder-RPG.page de travail des dons</link><link>Pathfinder-RPG.Peau résineuse</link><link>Pathfinder-RPG.Pêcheur des grottes</link><link>Pathfinder-RPG.Pièges de rôdeur</link><link>Pathfinder-RPG.Pieuvre</link><link>Pathfinder-RPG.Pieuvre à anneaux bleus</link><link>Pathfinder-RPG.Pieuvre géante</link><link>Pathfinder-RPG.Piscodaémon</link><link>Pathfinder-RPG.Pixie</link><link>Pathfinder-RPG.Poisson diable</link><link>Pathfinder-RPG.Pouvoirs de rage</link><link>Pathfinder-RPG.Raktavarna</link><link>Pathfinder-RPG.Rôdeur infiltré (rôdeur)</link><link>Pathfinder-RPG.Roublard</link><link>Pathfinder-RPG.Roussalka</link><link>Pathfinder-RPG.Sang sauvage (ensorceleur)</link><link>Pathfinder-RPG.Sangsue géante</link><link>Pathfinder-RPG.Scéaduinar</link><link>Pathfinder-RPG.Serpent creux</link><link>Pathfinder-RPG.Seugathi</link><link>Pathfinder-RPG.Shantak</link><link>Pathfinder-RPG.Shoggti</link><link>Pathfinder-RPG.Siyokoy</link><link>Pathfinder-RPG.Slurk</link><link>Pathfinder-RPG.sous-type asura</link><link>Pathfinder-RPG.Sphère glaciale</link><link>Pathfinder-RPG.Strige</link><link>Pathfinder-RPG.Substances et objets spéciaux</link><link>Pathfinder-RPG.Succube</link><link>Pathfinder-RPG.Tableau récapitulatif des compétences</link><link>Pathfinder-RPG.Tableau récapitulatif des dons</link><link>Pathfinder-RPG.Talents</link><link>Pathfinder-RPG.Tatzlwyrm</link><link>Pathfinder-RPG.temp-MainPage</link><link>Pathfinder-RPG.Tetori (moine)</link><link>Pathfinder-RPG.Thrasfyr</link><link>Pathfinder-RPG.Tieffelin</link><link>Pathfinder-RPG.Titan hécatonchire</link><link>Pathfinder-RPG.Toile (capacité)</link><link>Pathfinder-RPG.Toile daraignée</link><link>Pathfinder-RPG.Tojanida</link><link>Pathfinder-RPG.Traqueur sans visage</link><link>Pathfinder-RPG.Tripurasura</link><link>Pathfinder-RPG.type Aberration</link><link>Pathfinder-RPG.type Fée</link><link>Pathfinder-RPG.Upasunda</link><link>Pathfinder-RPG.Variantes de canalisation</link><link>Pathfinder-RPG.Ver du néant</link><link>Pathfinder-RPG.Viflin</link><link>Pathfinder-RPG.Vishkanya</link></inLinks>
  <outLinks><link>Pathfinder-RPG.Dextérité</link><link>Pathfinder-RPG.lutte</link><link>Pathfinder-RPG.DD</link><link>Pathfinder-RPG.BMO</link><link>Pathfinder-RPG.Tableau récapitulatif des armes</link><link>Pathfinder-RPG.Contrôle des plantes</link><link>Pathfinder-RPG.Corde animée</link><link>Pathfinder-RPG.Empire végétal</link><link>Pathfinder-RPG.Enchevêtrement</link><link>Pathfinder-RPG.Collet</link><link>Pathfinder-RPG.Immobilisé</link><link>Pathfinder-RPG.Agrippé</link><link>Pathfinder-RPG.Action complexe</link><link>Pathfinder-RPG.Action simple</link><link>Pathfinder-RPG.Discret</link></outLinks>
  <body><![CDATA[&lt;br /&gt;&lt;br /&gt;&lt;b&gt;Caract&#233;ristique associ&#233;e&lt;/b&gt; : &lt;a class=&quot;pagelink&quot; href=&quot;Caract&#233;ristiques.html#DEXTERITE&quot; title=&quot;La Dext&#233;rit&#233;&quot;&gt;Dext&#233;rit&#233;&lt;/a&gt;&lt;br /&gt;&lt;br /&gt;&lt;b&gt;Formation n&#233;cessaire&lt;/b&gt; : non &lt;br /&gt;&lt;br /&gt;&lt;b&gt;Malus d’armure&lt;/b&gt; : oui&lt;br /&gt;&lt;br /&gt;&lt;i&gt;Le personnage s’est entra&#238;n&#233; pour pouvoir se lib&#233;rer de liens et se soustraire aux &#233;treintes lors d’une &lt;a class=&quot;pagelink&quot; href=&quot;Manœuvres-Offensives.html#LUTTE&quot; title=&quot;lutte&quot;&gt;lutte&lt;/a&gt;.&lt;/i&gt;&lt;br /&gt;&lt;br /&gt;&lt;h2 class=&quot;separator&quot;&gt;Test de comp&#233;tence&lt;a class=&quot;headeranchor&quot; id=&quot;Test_de_comp&#233;tence_0&quot; href=&quot;#Test_de_comp&#233;tence_0&quot; title=&quot;Link to this Section&quot; style=&quot;visibility: hidden;&quot;&gt;&amp;nbsp;&lt;/a&gt;&lt;/h2&gt;
La table suivante indique les &lt;a class=&quot;pagelink&quot; href=&quot;Vocabulaire-Courant.html#DEGREDEDIFFICULTE&quot; title=&quot;DD&quot;&gt;DD&lt;/a&gt; associ&#233;s aux diff&#233;rentes formes d’entraves.&lt;br /&gt;&lt;br /&gt;&lt;center&gt;
&lt;table CLASS=&quot;tablo&quot;&gt;&lt;caption&gt;Entraves&lt;/caption&gt;&lt;tr CLASS=&quot;titre&quot;&gt;&lt;td&gt;Entraves&lt;/td&gt;&lt;td&gt;DD du test d’&#201;vasion&lt;/td&gt;&lt;/tr&gt;&lt;tr CLASS=&quot;premier&quot;&gt;&lt;td&gt;cordes, personnage ligot&#233;&lt;/td&gt;&lt;td&gt;20 + &lt;a class=&quot;pagelink&quot; href=&quot;Manœuvres-Offensives.html#BMO&quot; title=&quot;BMO&quot;&gt;BMO&lt;/a&gt; de l’individu&lt;br/&gt; qui a ligot&#233; le personnage&lt;/td&gt;&lt;/tr&gt;&lt;tr CLASS=&quot;alt&quot;&gt;&lt;td&gt;&lt;a class=&quot;pagelink&quot; href=&quot;Tableau-R&#233;capitulatif-Des-Armes.html&quot; title=&quot;Tableau r&#233;capitulatif des armes&quot;&gt;filet&lt;/a&gt;, sorts de &lt;i&gt;&lt;a class=&quot;pagelink&quot; href=&quot;Contr&#244;le-Des-Plantes.html&quot; title=&quot;Contr&#244;le des plantes&quot;&gt;contr&#244;le des plantes&lt;/a&gt;&lt;/i&gt;, &lt;i&gt;&lt;a class=&quot;pagelink&quot; href=&quot;Corde-Anim&#233;e.html&quot; title=&quot;Corde anim&#233;e&quot;&gt;corde anim&#233;e&lt;/a&gt;&lt;/i&gt;, &lt;i&gt;&lt;a class=&quot;pagelink&quot; href=&quot;Empire-V&#233;g&#233;tal.html&quot; title=&quot;Empire v&#233;g&#233;tal&quot;&gt;empire v&#233;g&#233;tal&lt;/a&gt;&lt;/i&gt; ou &lt;i&gt;&lt;a class=&quot;pagelink&quot; href=&quot;Enchev&#234;trement.html&quot; title=&quot;Enchev&#234;trement&quot;&gt;enchev&#234;trement&lt;/a&gt;&lt;/i&gt;&lt;/td&gt;&lt;td&gt;20&lt;/td&gt;&lt;/tr&gt;&lt;tr&gt;&lt;td&gt;sort de &lt;i&gt;&lt;a class=&quot;pagelink&quot; href=&quot;Collet.html&quot; title=&quot;Collet&quot;&gt;collet&lt;/a&gt;&lt;/i&gt;&lt;/td&gt;&lt;td&gt;23&lt;/td&gt;&lt;/tr&gt;&lt;tr CLASS=&quot;alt&quot;&gt;&lt;td&gt;menottes&lt;/td&gt;&lt;td&gt;30&lt;/td&gt;&lt;/tr&gt;&lt;tr&gt;&lt;td&gt;conduit &#233;troit&lt;/td&gt;&lt;td&gt;30&lt;/td&gt;&lt;/tr&gt;&lt;tr CLASS=&quot;alt&quot;&gt;&lt;td&gt;menottes de qualit&#233; sup&#233;rieure&lt;/td&gt;&lt;td&gt;35&lt;/td&gt;&lt;/tr&gt;&lt;tr&gt;&lt;td&gt;situation de &lt;a class=&quot;pagelink&quot; href=&quot;Manœuvres-Offensives.html#LUTTE&quot; title=&quot;lutte&quot;&gt;lutte&lt;/a&gt;&lt;/td&gt;&lt;td&gt;&lt;a class=&quot;pagelink&quot; href=&quot;Manœuvres-Offensives.html#BMO&quot; title=&quot;BMO&quot;&gt;BMO&lt;/a&gt; de l’adversaire&lt;/td&gt;&lt;/tr&gt;&lt;/table&gt;
&lt;/center&gt;&lt;br /&gt;&lt;br /&gt;&lt;b&gt;Cordes.&lt;/b&gt; Le &lt;a class=&quot;pagelink&quot; href=&quot;Vocabulaire-Courant.html#DEGREDEDIFFICULTE&quot; title=&quot;DD&quot;&gt;DD&lt;/a&gt; du test d’&#201;vasion du personnage est &#233;gal &#224; 20 + le &lt;a class=&quot;pagelink&quot; href=&quot;Manœuvres-Offensives.html#BMO&quot; title=&quot;BMO&quot;&gt;bonus de manœuvre offensive&lt;/a&gt; de l’individu qui l’a ligot&#233;.&lt;br /&gt;&lt;br /&gt;&lt;b&gt;Menottes et menottes de qualit&#233; sup&#233;rieure.&lt;/b&gt; Le DD des menottes est d&#233;termin&#233; par leur qualit&#233; (voir la table).&lt;br /&gt;&lt;br /&gt;&lt;b&gt;Conduit &#233;troit.&lt;/b&gt; Le &lt;a class=&quot;pagelink&quot; href=&quot;Vocabulaire-Courant.html#DEGREDEDIFFICULTE&quot; title=&quot;DD&quot;&gt;DD&lt;/a&gt; indiqu&#233; concerne les passages dans lesquels le personnage peut engager la t&#234;te, mais pas les &#233;paules (il lui faut donc se faufiler pour pouvoir entrer). Si le passage est suffisamment long, plusieurs tests de comp&#233;tence peuvent &#234;tre n&#233;cessaires. Il est impossible de se faufiler dans un passage o&#249; on ne peut pas passer la t&#234;te.&lt;br /&gt;&lt;br /&gt;&lt;b&gt;Situation de lutte.&lt;/b&gt; Au cours d’une &lt;a class=&quot;pagelink&quot; href=&quot;Manœuvres-Offensives.html#LUTTE&quot; title=&quot;lutte&quot;&gt;lutte&lt;/a&gt;, le personnage peut choisir de faire un test d’&#201;vasion au lieu d’un test de manœuvre offensive pour se lib&#233;rer d’une &lt;a class=&quot;pagelink&quot; href=&quot;Manœuvres-Offensives.html#LUTTE&quot; title=&quot;lutte&quot;&gt;&#233;treinte&lt;/a&gt; ou encore pour se d&#233;gager d’une situation o&#249; il est &lt;a class=&quot;pagelink&quot; href=&quot;&#201;tats-Pr&#233;judiciables.html#Immobilis&#233;&quot; title=&quot;Immobilis&#233;&quot;&gt;immobilis&#233;&lt;/a&gt; (et devenir simplement &lt;a class=&quot;pagelink&quot; href=&quot;&#201;tats-Pr&#233;judiciables.html#Agripp&#233;&quot; title=&quot;Agripp&#233;&quot;&gt;agripp&#233;&lt;/a&gt;).&lt;br /&gt;&lt;br /&gt;&lt;h2 class=&quot;separator&quot;&gt;Action&lt;a class=&quot;headeranchor&quot; id=&quot;Action_1&quot; href=&quot;#Action_1&quot; title=&quot;Link to this Section&quot; style=&quot;visibility: hidden;&quot;&gt;&amp;nbsp;&lt;/a&gt;&lt;/h2&gt;
Il faut une minute de travail pour tenter de se lib&#233;rer de liens, de menottes ou d’entraves d’une autre sorte (&#224; l’exception d’une lutte). &#201;chapper &#224; un &lt;a class=&quot;pagelink&quot; href=&quot;Tableau-R&#233;capitulatif-Des-Armes.html&quot; title=&quot;Tableau r&#233;capitulatif des armes&quot;&gt;filet&lt;/a&gt; ou un sort de &lt;i&gt;&lt;a class=&quot;pagelink&quot; href=&quot;Contr&#244;le-Des-Plantes.html&quot; title=&quot;Contr&#244;le des plantes&quot;&gt;contr&#244;le des plantes&lt;/a&gt;&lt;/i&gt;, &lt;i&gt;&lt;a class=&quot;pagelink&quot; href=&quot;Corde-Anim&#233;e.html&quot; title=&quot;Corde anim&#233;e&quot;&gt;corde anim&#233;e&lt;/a&gt;&lt;/i&gt;, &lt;i&gt;&lt;a class=&quot;pagelink&quot; href=&quot;Empire-V&#233;g&#233;tal.html&quot; title=&quot;Empire v&#233;g&#233;tal&quot;&gt;empire v&#233;g&#233;tal&lt;/a&gt;&lt;/i&gt; ou &lt;i&gt;&lt;a class=&quot;pagelink&quot; href=&quot;Enchev&#234;trement.html&quot; title=&quot;Enchev&#234;trement&quot;&gt;enchev&#234;trement&lt;/a&gt;&lt;/i&gt; n&#233;cessite une &lt;a class=&quot;pagelink&quot; href=&quot;Types-Dactions.html#COMPLEXE&quot; title=&quot;Action complexe&quot;&gt;action complexe&lt;/a&gt;. Tenter de se lib&#233;rer lors d’une &lt;a class=&quot;pagelink&quot; href=&quot;Manœuvres-Offensives.html#LUTTE&quot; title=&quot;lutte&quot;&gt;lutte&lt;/a&gt; est une &lt;a class=&quot;pagelink&quot; href=&quot;Types-Dactions.html#SIMPLE&quot; title=&quot;Action simple&quot;&gt;action simple&lt;/a&gt;. Se faufiler par un conduit &#233;troit prend au moins une minute, peut-&#234;tre plus en fonction de la longueur du passage.&lt;br /&gt;&lt;br /&gt;&lt;h2 class=&quot;separator&quot;&gt;Nouvelles tentatives&lt;a class=&quot;headeranchor&quot; id=&quot;Nouvelles_tentatives_2&quot; href=&quot;#Nouvelles_tentatives_2&quot; title=&quot;Link to this Section&quot; style=&quot;visibility: hidden;&quot;&gt;&amp;nbsp;&lt;/a&gt;&lt;/h2&gt;
Variable. Le personnage peut multiplier les tests de comp&#233;tence s’il progresse dans un passage &#233;troit. Si la situation le permet, il peut effectuer de nouveaux tests et m&#234;me faire 20 tant que personne ne s’oppose activement &#224; ses efforts. Si le DD pour se lib&#233;rer de liens est sup&#233;rieur &#224; 20 + le bonus d’&#201;vasion du personnage, celui-ci ne peut pas s’en lib&#233;rer gr&#226;ce &#224; cette comp&#233;tence.&lt;br /&gt;&lt;br /&gt;&lt;h2 class=&quot;separator&quot;&gt;Sp&#233;cial&lt;a class=&quot;headeranchor&quot; id=&quot;Sp&#233;cial_3&quot; href=&quot;#Sp&#233;cial_3&quot; title=&quot;Link to this Section&quot; style=&quot;visibility: hidden;&quot;&gt;&amp;nbsp;&lt;/a&gt;&lt;/h2&gt;
Un personnage poss&#233;dant le don &lt;a class=&quot;pagelink&quot; href=&quot;Discret.html&quot; title=&quot;Discret&quot;&gt;Discret&lt;/a&gt; obtient un bonus aux tests d’&#201;vasion.
]]></body>
  <raw><![CDATA[{s:MenuCompétences}

'''Caractéristique associée''' : [[Dextérité]]

'''Formation nécessaire''' : non 

'''Malus d’armure''' : oui

''Le personnage s’est entraîné pour pouvoir se libérer de liens et se soustraire aux étreintes lors d’une [[lutte]].''

===Test de compétence===

La table suivante indique les [[DD]] associés aux différentes formes d’entraves.

<center>
{| CLASS="tablo"
|+ Entraves
|- CLASS="titre"
| Entraves
| DD du test d’Évasion
|- CLASS="premier"
| cordes, personnage ligoté
| 20 + [[BMO]] de l’individu<br/> qui a ligoté le personnage
|- CLASS="alt"
| [[Tableau récapitulatif des armes|filet]], sorts de ''[[contrôle des plantes]]'', ''[[corde animée]]'', ''[[empire végétal]]'' ou ''[[enchevêtrement]]''
| 20
|-
| sort de ''[[collet]]''
| 23
|- CLASS="alt"
| menottes
| 30
|-
| conduit étroit
| 30
|- CLASS="alt"
| menottes de qualité supérieure
| 35
|-
| situation de [[lutte]]
| [[BMO]] de l’adversaire
|}
</center>

'''Cordes.''' Le [[DD]] du test d’Évasion du personnage est égal à 20 + le [[BMO|bonus de manœuvre offensive]] de l’individu qui l’a ligoté.

'''Menottes et menottes de qualité supérieure.''' Le DD des menottes est déterminé par leur qualité (voir la table).

'''Conduit étroit.''' Le [[DD]] indiqué concerne les passages dans lesquels le personnage peut engager la tête, mais pas les épaules (il lui faut donc se faufiler pour pouvoir entrer). Si le passage est suffisamment long, plusieurs tests de compétence peuvent être nécessaires. Il est impossible de se faufiler dans un passage où on ne peut pas passer la tête.

'''Situation de lutte.''' Au cours d’une [[lutte]], le personnage peut choisir de faire un test d’Évasion au lieu d’un test de manœuvre offensive pour se libérer d’une [[lutte|étreinte]] ou encore pour se dégager d’une situation où il est [[immobilisé]] (et devenir simplement [[agrippé]]).

===Action===

Il faut une minute de travail pour tenter de se libérer de liens, de menottes ou d’entraves d’une autre sorte (à l’exception d’une lutte). Échapper à un [[Tableau récapitulatif des armes|filet]] ou un sort de ''[[contrôle des plantes]]'', ''[[corde animée]]'', ''[[empire végétal]]'' ou ''[[enchevêtrement]]'' nécessite une [[action complexe]]. Tenter de se libérer lors d’une [[lutte]] est une [[action simple]]. Se faufiler par un conduit étroit prend au moins une minute, peut-être plus en fonction de la longueur du passage.

===Nouvelles tentatives===

Variable. Le personnage peut multiplier les tests de compétence s’il progresse dans un passage étroit. Si la situation le permet, il peut effectuer de nouveaux tests et même faire 20 tant que personne ne s’oppose activement à ses efforts. Si le DD pour se libérer de liens est supérieur à 20 + le bonus d’Évasion du personnage, celui-ci ne peut pas s’en libérer grâce à cette compétence.

===Spécial===

Un personnage possédant le don [[Discret]] obtient un bonus aux tests d’Évasion.]]></raw>
  <fullName>Pathfinder-RPG.Évasion</fullName>
</wikiPage>